{
    "producer": "monnify",
    "title": "monnify",
    "description": "The Monnify API Docs has been grouped to help you easily find what you need and guide you through the process of integration. Simply read through the use cases and click on which one you think is closest to yours.",
    "image": "https://s3.amazonaws.com/services.apiplatform.io/service-providers/Service%20providers%20-%20resized%20logo's/Resized%20Logo's/Monnify.png",
    "url": "https://monnify.com/",
    "authorization": [
        {
            "authtype": "Bearer Token",
            "authattributes": [
                {
                    "key": "token",
                    "displayname": "Token"
                }
            ]
        },
        {
            "authtype": "OAuth 2.0",
            "authattributes": [
                {
                    "key": "base_url",
                    "displayname": "Authorize URL"
                },
                {
                    "key": "token_url",
                    "displayname": "Access Token URL"
                },
                {
                    "key": "refreshtoken_url",
                    "displayname": "Refresh Token URL"
                },
                {
                    "key": "client_id",
                    "displayname": "Client ID"
                },
                {
                    "key": "client_secret",
                    "displayname": "Client Secret"
                },
                {
                    "key": "scope",
                    "displayname": "Scope"
                }
            ]
        },
        {
            "authtype": "API Key",
            "authattributes": [
                {
                    "key": "key",
                    "displayname": "Key"
                },
                {
                    "key": "value",
                    "displayname": "Value"
                }
            ]
        },
        {
            "authtype": "Basic Authentication",
            "authattributes": [
                {
                    "key": "username",
                    "displayname": "Username"
                },
                {
                    "key": "password",
                    "displayname": "Password"
                }
            ]
        }
    ],
    "partner": "services",
    "account": "services",
    "isPromoted": false,
    "id": 346
}