[
    {
        "id": 119223,
        "executor_type": "THIRDPARTY",
        "executor_name": "deleteSingleAnnotation",
        "executor_version": "v1",
        "executor_display_name": "Delete Single Annotation",
        "executor_description": "This endpoint deletes the annotation with the given name in the specified project (Project header).",
        "executor_category": "Annotations",
        "executor_category_group": "Annotations",
        "service_provider": "noblnine",
        "executor_scope": null,
        "partner": "b2b",
        "account_id": "b2b",
        "executor_method_type": "DELETE",
        "apiUrl": "https://app.nobl9.com/api/annotations/{name}",
        "dataroot": null,
        "pathParams": [
            {
                "key": "name",
                "value": "",
                "description": "Annotation name"
            }
        ],
        "queryParams": [],
        "headers": [
            {
                "key": "Organization",
                "value": "",
                "description": "Your organization ID. You can find it in the Nobl9 UI, in the Settings > Account.",
                "req": false
            },
            {
                "key": "Project",
                "value": "",
                "description": "Project name, must be explicit, wildcard is not supported",
                "req": false
            }
        ],
        "authModel": {
            "authType": "bearer_token",
            "authAttributes": {}
        },
        "requestBody": {
            "value": "",
            "key": "payload",
            "description": "Document in JSON format",
            "annotation": "RequestBody"
        },
        "prerequisites": null,
        "executors": null,
        "functions": null,
        "responseAttributes": [
            {
                "attributeName": null,
                "displayName": null,
                "description": null,
                "type": null,
                "size": 0,
                "precision": 0,
                "autoIncrement": false,
                "defaultValue": null,
                "subType": [],
                "attributeType": "None",
                "required": false,
                "dataStoragePolicy": "None",
                "apiAccessPolicy": "None",
                "displayPolicy": "None",
                "array": false,
                "customType": false,
                "updateOption": null,
                "previousAttributeName": null,
                "compliances": null
            }
        ],
        "response": null,
        "attributeMappings": null,
        "source": null,
        "block_attributes": null,
        "workflow_credentials": null,
        "disabled": false,
        "published": true,
        "scopeOfAccess": "public",
        "registeredAsIs": true,
        "creationTime": 1698731051270,
        "lastModifiedTime": 1698731051270,
        "executionLib": null,
        "isDocumentationPublished": true,
        "mockResponses": [
            {
                "statusCode": 403,
                "name": null,
                "statusText": null,
                "methodType": "GET",
                "message": "Forbidden",
                "description": null,
                "headers": [
                    {
                        "name": "Content-Type",
                        "value": "text/plain"
                    }
                ],
                "cookies": null,
                "responseAttributes": [],
                "sampleData": null
            },
            {
                "statusCode": 400,
                "name": null,
                "statusText": null,
                "methodType": "GET",
                "message": "Bad Request",
                "description": null,
                "headers": [
                    {
                        "name": "Content-Type",
                        "value": "text/plain"
                    }
                ],
                "cookies": null,
                "responseAttributes": [],
                "sampleData": null
            },
            {
                "statusCode": 500,
                "name": null,
                "statusText": null,
                "methodType": "GET",
                "message": "Internal Server Error",
                "description": null,
                "headers": [
                    {
                        "name": "Content-Type",
                        "value": "text/plain"
                    }
                ],
                "cookies": null,
                "responseAttributes": [],
                "sampleData": null
            },
            {
                "statusCode": 204,
                "name": null,
                "statusText": null,
                "methodType": "DELETE",
                "message": "Annotation was deleted, or not found",
                "description": null,
                "headers": [
                    {
                        "name": "Content-Type",
                        "value": "text/plain"
                    }
                ],
                "cookies": null,
                "responseAttributes": [],
                "sampleData": null
            }
        ],
        "isMockResponseEnabled": false,
        "block_id": null,
        "gatewaySettings": null,
        "apiQueryModel": null,
        "properties": null,
        "vid": null,
        "nid": null
    },
    {
        "id": 119221,
        "executor_type": "THIRDPARTY",
        "executor_name": "getaListofAnnotations",
        "executor_version": "v1",
        "executor_display_name": "Get a List of Annotations",
        "executor_description": "Get Annotations with the values specified in a request.",
        "executor_category": "Annotations",
        "executor_category_group": "Annotations",
        "service_provider": "noblnine",
        "executor_scope": null,
        "partner": "b2b",
        "account_id": "b2b",
        "executor_method_type": "GET",
        "apiUrl": "https://app.nobl9.com/api/annotations",
        "dataroot": null,
        "pathParams": [],
        "queryParams": [
            {
                "key": "name",
                "value": "",
                "description": "The name of the annotation. You can provide multiple names. The query matches all the names.",
                "req": false
            },
            {
                "key": "slo",
                "value": "",
                "description": "The name of the SLO to which the annotations are attached.",
                "req": false
            },
            {
                "key": "from",
                "value": "",
                "description": "Matches Annotation.startTime. Start time of the Annotation period in RFC3339 format.",
                "req": false
            },
            {
                "key": "to",
                "value": "",
                "description": "Matches Annotation.endTime. End time of the Annotation period in RFC3339 format.",
                "req": false
            }
        ],
        "headers": [
            {
                "key": "Organization",
                "value": "",
                "description": "Your organization ID. You can find it in the Nobl9 UI, in the Settings > Account.",
                "req": false
            },
            {
                "key": "Project",
                "value": "",
                "description": "Project name, must conform to DNS (RFC 1123 format). might be wildcard with *.",
                "req": false
            }
        ],
        "authModel": {
            "authType": "bearer_token",
            "authAttributes": {}
        },
        "requestBody": {
            "value": "",
            "key": "payload",
            "description": "Document in JSON format",
            "annotation": "RequestBody"
        },
        "prerequisites": null,
        "executors": null,
        "functions": null,
        "responseAttributes": [
            {
                "attributeName": null,
                "displayName": null,
                "description": null,
                "type": null,
                "size": 0,
                "precision": 0,
                "autoIncrement": false,
                "defaultValue": null,
                "subType": [],
                "attributeType": "None",
                "required": false,
                "dataStoragePolicy": "None",
                "apiAccessPolicy": "None",
                "displayPolicy": "None",
                "array": false,
                "customType": false,
                "updateOption": null,
                "previousAttributeName": null,
                "compliances": null
            }
        ],
        "response": null,
        "attributeMappings": null,
        "source": null,
        "block_attributes": null,
        "workflow_credentials": null,
        "disabled": false,
        "published": true,
        "scopeOfAccess": "public",
        "registeredAsIs": true,
        "creationTime": 1698730285534,
        "lastModifiedTime": 1698730285534,
        "executionLib": null,
        "isDocumentationPublished": true,
        "mockResponses": [
            {
                "statusCode": 200,
                "name": null,
                "statusText": null,
                "methodType": "GET",
                "message": "OK",
                "description": null,
                "headers": [
                    {
                        "name": "Content-Type",
                        "value": "application/json"
                    }
                ],
                "cookies": null,
                "responseAttributes": [],
                "sampleData": [
                    {
                        "description": "string",
                        "endTime": "2006-01-02T17:04:05Z",
                        "name": "my-annotation-name",
                        "project": "default",
                        "slo": "my-slo-name",
                        "startTime": "2006-01-02T17:04:05Z",
                        "status": {
                            "updatedAt": "2006-01-02T17:04:05Z"
                        }
                    }
                ]
            },
            {
                "statusCode": 403,
                "name": null,
                "statusText": null,
                "methodType": "GET",
                "message": "Forbidden",
                "description": null,
                "headers": [
                    {
                        "name": "Content-Type",
                        "value": "text/plain"
                    }
                ],
                "cookies": null,
                "responseAttributes": [],
                "sampleData": null
            },
            {
                "statusCode": 400,
                "name": null,
                "statusText": null,
                "methodType": "GET",
                "message": "Bad Request",
                "description": null,
                "headers": [
                    {
                        "name": "Content-Type",
                        "value": "text/plain"
                    }
                ],
                "cookies": null,
                "responseAttributes": [],
                "sampleData": null
            },
            {
                "statusCode": 500,
                "name": null,
                "statusText": null,
                "methodType": "GET",
                "message": "Internal Server Error",
                "description": null,
                "headers": [
                    {
                        "name": "Content-Type",
                        "value": "text/plain"
                    }
                ],
                "cookies": null,
                "responseAttributes": [],
                "sampleData": null
            }
        ],
        "isMockResponseEnabled": false,
        "block_id": null,
        "gatewaySettings": null,
        "apiQueryModel": null,
        "properties": null,
        "vid": null,
        "nid": null
    },
    {
        "id": 119222,
        "executor_type": "THIRDPARTY",
        "executor_name": "createSingleAnnotation",
        "executor_version": "v1",
        "executor_display_name": "Create Single Annotation",
        "executor_description": "ou can update Annotations using a standard PUT request. This method will create a new annotation unless the annotation with the provided name (i.e. specified in the body of the JSON object) does not exist in the specified Project.  In addition, you must also provide all the remaining parameters even if you want to update just one of them (effectively, this command acts like a REPLACE command).",
        "executor_category": "Annotations",
        "executor_category_group": "Annotations",
        "service_provider": "noblnine",
        "executor_scope": null,
        "partner": "b2b",
        "account_id": "b2b",
        "executor_method_type": "POST",
        "apiUrl": "https://app.nobl9.com/api/annotations",
        "dataroot": null,
        "pathParams": [],
        "queryParams": [
            {
                "key": "name",
                "value": "",
                "description": "The name of the annotation. You can provide multiple names. The query matches all the names.",
                "req": false
            },
            {
                "key": "slo",
                "value": "",
                "description": "The name of the SLO to which the annotations are attached.",
                "req": false
            },
            {
                "key": "from",
                "value": "",
                "description": "Matches Annotation.startTime. Start time of the Annotation period in RFC3339 format.",
                "req": false
            },
            {
                "key": "to",
                "value": "",
                "description": "Matches Annotation.endTime. End time of the Annotation period in RFC3339 format.",
                "req": false
            }
        ],
        "headers": [
            {
                "key": "Content-Type",
                "value": "application/json",
                "description": "",
                "req": false
            },
            {
                "key": "Organization",
                "value": "",
                "description": "Your organization ID. You can find it in the Nobl9 UI, in the Settings > Account.",
                "req": false
            }
        ],
        "authModel": {
            "authType": "bearer_token",
            "authAttributes": {}
        },
        "requestBody": {
            "value": {
                "description": "string",
                "endTime": "2006-01-02T17:04:05Z",
                "name": "name",
                "project": "default",
                "slo": "my-slo-name",
                "startTime": "2006-01-02T17:04:05Z"
            },
            "key": "payload",
            "description": "Document in JSON format",
            "annotation": "RequestBody"
        },
        "prerequisites": null,
        "executors": null,
        "functions": null,
        "responseAttributes": [
            {
                "attributeName": null,
                "displayName": null,
                "description": null,
                "type": null,
                "size": 0,
                "precision": 0,
                "autoIncrement": false,
                "defaultValue": null,
                "subType": [],
                "attributeType": "None",
                "required": false,
                "dataStoragePolicy": "None",
                "apiAccessPolicy": "None",
                "displayPolicy": "None",
                "array": false,
                "customType": false,
                "updateOption": null,
                "previousAttributeName": null,
                "compliances": null
            }
        ],
        "response": null,
        "attributeMappings": null,
        "source": null,
        "block_attributes": null,
        "workflow_credentials": null,
        "disabled": false,
        "published": true,
        "scopeOfAccess": "public",
        "registeredAsIs": true,
        "creationTime": 1698730784721,
        "lastModifiedTime": 1698730784721,
        "executionLib": null,
        "isDocumentationPublished": true,
        "mockResponses": [
            {
                "statusCode": 200,
                "name": null,
                "statusText": null,
                "methodType": "GET",
                "message": "Created annotation",
                "description": null,
                "headers": [
                    {
                        "name": "Content-Type",
                        "value": "application/json"
                    }
                ],
                "cookies": null,
                "responseAttributes": [],
                "sampleData": {
                    "description": "string",
                    "endTime": "2006-01-02T17:04:05Z",
                    "name": "my-annotation-name",
                    "project": "default",
                    "slo": "my-slo-name",
                    "startTime": "2006-01-02T17:04:05Z",
                    "status": {
                        "updatedAt": "2006-01-02T17:04:05Z"
                    }
                }
            },
            {
                "statusCode": 403,
                "name": null,
                "statusText": null,
                "methodType": "GET",
                "message": "Forbidden",
                "description": null,
                "headers": [
                    {
                        "name": "Content-Type",
                        "value": "text/plain"
                    }
                ],
                "cookies": null,
                "responseAttributes": [],
                "sampleData": null
            },
            {
                "statusCode": 400,
                "name": null,
                "statusText": null,
                "methodType": "GET",
                "message": "Bad Request",
                "description": null,
                "headers": [
                    {
                        "name": "Content-Type",
                        "value": "text/plain"
                    }
                ],
                "cookies": null,
                "responseAttributes": [],
                "sampleData": null
            },
            {
                "statusCode": 500,
                "name": null,
                "statusText": null,
                "methodType": "GET",
                "message": "Internal Server Error",
                "description": null,
                "headers": [
                    {
                        "name": "Content-Type",
                        "value": "text/plain"
                    }
                ],
                "cookies": null,
                "responseAttributes": [],
                "sampleData": null
            },
            {
                "statusCode": 404,
                "name": null,
                "statusText": null,
                "methodType": "POST",
                "message": "One of the resources referenced in query or payload was not found",
                "description": null,
                "headers": [
                    {
                        "name": "Content-Type",
                        "value": "text/plain"
                    }
                ],
                "cookies": null,
                "responseAttributes": [],
                "sampleData": null
            },
            {
                "statusCode": 409,
                "name": null,
                "statusText": null,
                "methodType": "POST",
                "message": "Annotation already exists",
                "description": null,
                "headers": [
                    {
                        "name": "Content-Type",
                        "value": "text/plain"
                    }
                ],
                "cookies": null,
                "responseAttributes": [],
                "sampleData": null
            }
        ],
        "isMockResponseEnabled": false,
        "block_id": null,
        "gatewaySettings": null,
        "apiQueryModel": null,
        "properties": null,
        "vid": null,
        "nid": null
    },
    {
        "id": 119224,
        "executor_type": "THIRDPARTY",
        "executor_name": "upsertSingleAnnotation",
        "executor_version": "v1",
        "executor_display_name": "Upsert Single Annotation",
        "executor_description": "Create a new Annotation for any event within one of your SLOs.",
        "executor_category": "Annotations",
        "executor_category_group": "Annotations",
        "service_provider": "noblnine",
        "executor_scope": null,
        "partner": "b2b",
        "account_id": "b2b",
        "executor_method_type": "PUT",
        "apiUrl": "https://app.nobl9.com/api/annotations/{name}",
        "dataroot": null,
        "pathParams": [
            {
                "key": "name",
                "value": "",
                "description": "Annotation name"
            }
        ],
        "queryParams": [],
        "headers": [
            {
                "key": "Organization",
                "value": "",
                "description": "Your organization ID. You can find it in the Nobl9 UI, in the Settings > Account.",
                "req": false
            },
            {
                "key": "Content-Type",
                "value": "application/json",
                "description": "",
                "req": false
            }
        ],
        "authModel": {
            "authType": "bearer_token",
            "authAttributes": {}
        },
        "requestBody": {
            "value": {
                "description": "string",
                "endTime": "2006-01-02T17:04:05Z",
                "project": "default",
                "slo": "my-slo-name",
                "startTime": "2006-01-02T17:04:05Z"
            },
            "key": "payload",
            "description": "Document in JSON format",
            "annotation": "RequestBody"
        },
        "prerequisites": null,
        "executors": null,
        "functions": null,
        "responseAttributes": [
            {
                "attributeName": null,
                "displayName": null,
                "description": null,
                "type": null,
                "size": 0,
                "precision": 0,
                "autoIncrement": false,
                "defaultValue": null,
                "subType": [],
                "attributeType": "None",
                "required": false,
                "dataStoragePolicy": "None",
                "apiAccessPolicy": "None",
                "displayPolicy": "None",
                "array": false,
                "customType": false,
                "updateOption": null,
                "previousAttributeName": null,
                "compliances": null
            }
        ],
        "response": null,
        "attributeMappings": null,
        "source": null,
        "block_attributes": null,
        "workflow_credentials": null,
        "disabled": false,
        "published": true,
        "scopeOfAccess": "public",
        "registeredAsIs": true,
        "creationTime": 1698731383001,
        "lastModifiedTime": 1698731383001,
        "executionLib": null,
        "isDocumentationPublished": true,
        "mockResponses": [
            {
                "statusCode": 403,
                "name": null,
                "statusText": null,
                "methodType": "GET",
                "message": "Forbidden",
                "description": null,
                "headers": [
                    {
                        "name": "Content-Type",
                        "value": "text/plain"
                    }
                ],
                "cookies": null,
                "responseAttributes": [],
                "sampleData": null
            },
            {
                "statusCode": 400,
                "name": null,
                "statusText": null,
                "methodType": "PUT",
                "message": "Bad Request",
                "description": null,
                "headers": [
                    {
                        "name": "Content-Type",
                        "value": "text/plain"
                    }
                ],
                "cookies": null,
                "responseAttributes": [],
                "sampleData": null
            },
            {
                "statusCode": 500,
                "name": null,
                "statusText": null,
                "methodType": "GET",
                "message": "Internal Server Error",
                "description": null,
                "headers": [
                    {
                        "name": "Content-Type",
                        "value": "text/plain"
                    }
                ],
                "cookies": null,
                "responseAttributes": [],
                "sampleData": null
            },
            {
                "statusCode": 200,
                "name": null,
                "statusText": null,
                "methodType": "PUT",
                "message": "Created or replaced annotation",
                "description": null,
                "headers": [
                    {
                        "name": "Content-Type",
                        "value": "application/json"
                    }
                ],
                "cookies": null,
                "responseAttributes": [],
                "sampleData": {
                    "description": "string",
                    "endTime": "2006-01-02T17:04:05Z",
                    "name": "my-annotation-name",
                    "project": "default",
                    "slo": "my-slo-name",
                    "startTime": "2006-01-02T17:04:05Z",
                    "status": {
                        "updatedAt": "2006-01-02T17:04:05Z"
                    }
                }
            },
            {
                "statusCode": 404,
                "name": null,
                "statusText": null,
                "methodType": "PUT",
                "message": "One of the resources referenced in query or payload was not found",
                "description": null,
                "headers": [
                    {
                        "name": "Content-Type",
                        "value": "text/plain"
                    }
                ],
                "cookies": null,
                "responseAttributes": [],
                "sampleData": null
            }
        ],
        "isMockResponseEnabled": false,
        "block_id": null,
        "gatewaySettings": null,
        "apiQueryModel": null,
        "properties": null,
        "vid": null,
        "nid": null
    },
    {
        "id": 119216,
        "executor_type": "THIRDPARTY",
        "executor_name": "findSLObyname",
        "executor_version": "v1",
        "executor_display_name": "Find SLO by name",
        "executor_description": "Returns a single SLO",
        "executor_category": "SLO",
        "executor_category_group": "SLO",
        "service_provider": "noblnine",
        "executor_scope": null,
        "partner": "b2b",
        "account_id": "b2b",
        "executor_method_type": "GET",
        "apiUrl": "https://app.nobl9.com/api/v1/slos/{sloName}",
        "dataroot": null,
        "pathParams": [
            {
                "key": "sloName",
                "value": "",
                "description": "Name of the SLO to return."
            }
        ],
        "queryParams": [],
        "headers": [
            {
                "key": "Organization",
                "value": "",
                "description": "ID of your organization.",
                "req": false
            },
            {
                "key": "apikey",
                "value": "",
                "description": ""
            },
            {
                "key": "project",
                "value": "",
                "description": "Filters results by a specific project.",
                "req": false
            }
        ],
        "authModel": {
            "authType": "bearer_token",
            "authAttributes": {}
        },
        "requestBody": {
            "value": "",
            "key": "payload",
            "description": "Document in JSON format",
            "annotation": "RequestBody"
        },
        "prerequisites": null,
        "executors": null,
        "functions": null,
        "responseAttributes": [
            {
                "attributeName": null,
                "displayName": null,
                "description": null,
                "type": null,
                "size": 0,
                "precision": 0,
                "autoIncrement": false,
                "defaultValue": null,
                "subType": [],
                "attributeType": "None",
                "required": false,
                "dataStoragePolicy": "None",
                "apiAccessPolicy": "None",
                "displayPolicy": "None",
                "array": false,
                "customType": false,
                "updateOption": null,
                "previousAttributeName": null,
                "compliances": null
            }
        ],
        "response": null,
        "attributeMappings": null,
        "source": null,
        "block_attributes": null,
        "workflow_credentials": null,
        "disabled": false,
        "published": true,
        "scopeOfAccess": "public",
        "registeredAsIs": true,
        "creationTime": 1698672111116,
        "lastModifiedTime": 1698672111116,
        "executionLib": null,
        "isDocumentationPublished": true,
        "mockResponses": [
            {
                "statusCode": 200,
                "name": null,
                "statusText": null,
                "methodType": "GET",
                "message": "Successful operation",
                "description": null,
                "headers": [
                    {
                        "name": "Content-Type",
                        "value": "application/json"
                    }
                ],
                "cookies": null,
                "responseAttributes": [],
                "sampleData": {
                    "name": "sample-latency-slo",
                    "displayName": "Sample latency SLO",
                    "description": "This is a sample latency SLO",
                    "project": "sample-project",
                    "service": "sample-service",
                    "objectives": [
                        {
                            "name": "objective-1",
                            "displayName": "Good",
                            "target": 0.5,
                            "burnRate": 0,
                            "errorBudgetRemaining": 14397.305873435587,
                            "errorBudgetRemainingPercentage": 0.5951267308794467
                        }
                    ],
                    "createdAt": "2019-08-24T14:15:22Z",
                    "composite": {
                        "target": 0.9,
                        "burnRate": 0,
                        "errorBudgetRemaining": 14397.305873435587,
                        "errorBudgetRemainingPercentage": 0.5951267308794467,
                        "burnRateCondition": {
                            "value": 0,
                            "operator": "gt"
                        }
                    }
                }
            },
            {
                "statusCode": 401,
                "name": null,
                "statusText": null,
                "methodType": "GET",
                "message": "Authentication credentials not valid",
                "description": null,
                "headers": [
                    {
                        "name": "Content-Type",
                        "value": "text/plain"
                    }
                ],
                "cookies": null,
                "responseAttributes": [],
                "sampleData": null
            },
            {
                "statusCode": 429,
                "name": null,
                "statusText": null,
                "methodType": "GET",
                "message": "API call exceeded the rate limit",
                "description": null,
                "headers": [
                    {
                        "name": "Content-Type",
                        "value": "text/plain"
                    }
                ],
                "cookies": null,
                "responseAttributes": [],
                "sampleData": null
            },
            {
                "statusCode": 403,
                "name": null,
                "statusText": null,
                "methodType": "GET",
                "message": "Access to the requested SLO is forbidden",
                "description": null,
                "headers": [
                    {
                        "name": "Content-Type",
                        "value": "text/plain"
                    }
                ],
                "cookies": null,
                "responseAttributes": [],
                "sampleData": null
            },
            {
                "statusCode": 404,
                "name": null,
                "statusText": null,
                "methodType": "GET",
                "message": "SLO not found",
                "description": null,
                "headers": [
                    {
                        "name": "Content-Type",
                        "value": "text/plain"
                    }
                ],
                "cookies": null,
                "responseAttributes": [],
                "sampleData": null
            }
        ],
        "isMockResponseEnabled": false,
        "block_id": null,
        "gatewaySettings": null,
        "apiQueryModel": null,
        "properties": null,
        "vid": null,
        "nid": null
    },
    {
        "id": 119210,
        "executor_type": "THIRDPARTY",
        "executor_name": "listSLOs",
        "executor_version": "v1",
        "executor_display_name": "List SLOs",
        "executor_description": "Return a SLO list for a specific organization",
        "executor_category": "SLO",
        "executor_category_group": "SLO",
        "service_provider": "noblnine",
        "executor_scope": null,
        "partner": "b2b",
        "account_id": "b2b",
        "executor_method_type": "GET",
        "apiUrl": "https://app.nobl9.com/api/v1/slos",
        "dataroot": null,
        "pathParams": [],
        "queryParams": [],
        "headers": [
            {
                "key": "Organization",
                "value": "",
                "description": "ID of your organization.",
                "req": false
            },
            {
                "key": "apikey",
                "value": "",
                "description": ""
            }
        ],
        "authModel": {
            "authType": "bearer_token",
            "authAttributes": {}
        },
        "requestBody": {
            "value": "",
            "key": "payload",
            "description": "Document in JSON format",
            "annotation": "RequestBody"
        },
        "prerequisites": null,
        "executors": null,
        "functions": null,
        "responseAttributes": [
            {
                "attributeName": null,
                "displayName": null,
                "description": null,
                "type": null,
                "size": 0,
                "precision": 0,
                "autoIncrement": false,
                "defaultValue": null,
                "subType": [],
                "attributeType": "None",
                "required": false,
                "dataStoragePolicy": "None",
                "apiAccessPolicy": "None",
                "displayPolicy": "None",
                "array": false,
                "customType": false,
                "updateOption": null,
                "previousAttributeName": null,
                "compliances": null
            }
        ],
        "response": null,
        "attributeMappings": null,
        "source": null,
        "block_attributes": null,
        "workflow_credentials": null,
        "disabled": false,
        "published": true,
        "scopeOfAccess": null,
        "registeredAsIs": true,
        "creationTime": 1698671238832,
        "lastModifiedTime": 1698672031503,
        "executionLib": null,
        "isDocumentationPublished": true,
        "mockResponses": [
            {
                "statusCode": 200,
                "name": null,
                "statusText": null,
                "methodType": "GET",
                "message": "Successful operation",
                "description": null,
                "headers": [
                    {
                        "name": "Content-Type",
                        "value": "application/json"
                    }
                ],
                "cookies": null,
                "responseAttributes": [],
                "sampleData": {
                    "data": [
                        {
                            "name": "sample-latency-slo",
                            "displayName": "Sample latency SLO",
                            "description": "This is a sample latency SLO",
                            "project": "sample-project",
                            "service": "sample-service",
                            "objectives": [
                                {
                                    "name": "objective-1",
                                    "displayName": "Good",
                                    "target": 0.5,
                                    "burnRate": 0,
                                    "errorBudgetRemaining": 14397.305873435587,
                                    "errorBudgetRemainingPercentage": 0.5951267308794467
                                }
                            ],
                            "createdAt": "2019-08-24T14:15:22Z",
                            "composite": {
                                "target": 0.9,
                                "burnRate": 0,
                                "errorBudgetRemaining": 14397.305873435587,
                                "errorBudgetRemainingPercentage": 0.5951267308794467,
                                "burnRateCondition": {
                                    "value": 0,
                                    "operator": "gt"
                                }
                            }
                        }
                    ],
                    "links": {
                        "self": "string",
                        "next": "string"
                    }
                }
            },
            {
                "statusCode": 401,
                "name": null,
                "statusText": null,
                "methodType": "GET",
                "message": "Authentication credentials not valid",
                "description": null,
                "headers": [
                    {
                        "name": "Content-Type",
                        "value": "text/plain"
                    }
                ],
                "cookies": null,
                "responseAttributes": [],
                "sampleData": null
            },
            {
                "statusCode": 429,
                "name": null,
                "statusText": null,
                "methodType": "GET",
                "message": "API call exceeded the rate limit",
                "description": null,
                "headers": [
                    {
                        "name": "Content-Type",
                        "value": "text/plain"
                    }
                ],
                "cookies": null,
                "responseAttributes": [],
                "sampleData": null
            }
        ],
        "isMockResponseEnabled": false,
        "block_id": null,
        "gatewaySettings": null,
        "apiQueryModel": null,
        "properties": {
            "showBodyParamDescription": false,
            "bodyParamDescription": []
        },
        "vid": null,
        "nid": null
    },
    {
        "id": 119204,
        "executor_type": "THIRDPARTY",
        "executor_name": "generateAccessToken",
        "executor_version": "v1",
        "executor_display_name": "Generate Access Token",
        "executor_description": "To generate access token, you must provide Authorization header with the Basic scheme.  The access token consists of your Client ID and Client Secret in the following format: clientId:clientSecret.",
        "executor_category": "AccessToken",
        "executor_category_group": "AccessToken",
        "service_provider": "noblnine",
        "executor_scope": null,
        "partner": "b2b",
        "account_id": "b2b",
        "executor_method_type": "POST",
        "apiUrl": "https://app.nobl9.com/api/accessToken",
        "dataroot": null,
        "pathParams": [],
        "queryParams": [],
        "headers": [
            {
                "key": "Content-Type",
                "value": "application/json",
                "description": "",
                "req": false
            },
            {
                "key": "Organization",
                "value": "",
                "description": "ID of your organization.",
                "req": false
            }
        ],
        "authModel": {
            "authType": "basic_authentication",
            "authAttributes": {
                "username": "",
                "password": ""
            }
        },
        "requestBody": {
            "value": {},
            "key": "payload",
            "description": "Document in JSON format",
            "annotation": "RequestBody"
        },
        "prerequisites": null,
        "executors": null,
        "functions": null,
        "responseAttributes": [
            {
                "attributeName": null,
                "displayName": null,
                "description": null,
                "type": null,
                "size": 0,
                "precision": 0,
                "autoIncrement": false,
                "defaultValue": null,
                "subType": [],
                "attributeType": "None",
                "required": false,
                "dataStoragePolicy": "None",
                "apiAccessPolicy": "None",
                "displayPolicy": "None",
                "array": false,
                "customType": false,
                "updateOption": null,
                "previousAttributeName": null,
                "compliances": null
            }
        ],
        "response": null,
        "attributeMappings": null,
        "source": null,
        "block_attributes": null,
        "workflow_credentials": null,
        "disabled": false,
        "published": true,
        "scopeOfAccess": null,
        "registeredAsIs": true,
        "creationTime": 1698669519794,
        "lastModifiedTime": 1698669824514,
        "executionLib": null,
        "isDocumentationPublished": true,
        "mockResponses": [
            {
                "statusCode": 200,
                "name": null,
                "statusText": null,
                "methodType": "POST",
                "message": "OK",
                "description": null,
                "headers": [
                    {
                        "name": "Content-Type",
                        "value": "application/json"
                    }
                ],
                "cookies": null,
                "responseAttributes": [],
                "sampleData": {
                    "access_token": "string"
                }
            },
            {
                "statusCode": 400,
                "name": null,
                "statusText": null,
                "methodType": "POST",
                "message": "Bad Request",
                "description": null,
                "headers": [
                    {
                        "name": "Content-Type",
                        "value": "text/plain"
                    }
                ],
                "cookies": null,
                "responseAttributes": [],
                "sampleData": null
            },
            {
                "statusCode": 401,
                "name": null,
                "statusText": null,
                "methodType": "POST",
                "message": "Unauthorized",
                "description": null,
                "headers": [
                    {
                        "name": "Content-Type",
                        "value": "text/plain"
                    }
                ],
                "cookies": null,
                "responseAttributes": [],
                "sampleData": null
            },
            {
                "statusCode": 403,
                "name": null,
                "statusText": null,
                "methodType": "POST",
                "message": "Forbidden",
                "description": null,
                "headers": [
                    {
                        "name": "Content-Type",
                        "value": "text/plain"
                    }
                ],
                "cookies": null,
                "responseAttributes": [],
                "sampleData": null
            },
            {
                "statusCode": 249,
                "name": null,
                "statusText": null,
                "methodType": "POST",
                "message": "API call exceeded the rate limit",
                "description": null,
                "headers": [
                    {
                        "name": "Content-Type",
                        "value": "text/plain"
                    }
                ],
                "cookies": null,
                "responseAttributes": [],
                "sampleData": null
            }
        ],
        "isMockResponseEnabled": false,
        "block_id": null,
        "gatewaySettings": null,
        "apiQueryModel": null,
        "properties": {
            "showBodyParamDescription": false,
            "bodyParamDescription": []
        },
        "vid": null,
        "nid": null
    }
]